eaiBat/__init__.py
eaiBat/eaiBat.py
eaiBat/evidenceGenerators/DocxEvidence.py
eaiBat/evidenceGenerators/MdEvidence.py
eaiBat/evidenceGenerators/__init__.py
evidenceGenerators/DocxEvidence.py
evidenceGenerators/MdEvidence.py
evidenceGenerators/__init__.py
tests/Attribute_test.py
tests/CreateEvidence_docx_test.py
tests/CreateEvidence_markdown_test.py
tests/Docx_insert_text_sql_file_test.py
tests/EvidenceFolder_test.py
tests/PushEvent_test.py
tests/__init__.py
tests/file_to_evidence_test.py
tests/helpers.py
eaibat-0.0.11.dist-info/LICENSE
eaibat-0.0.11.dist-info/METADATA
eaibat-0.0.11.dist-info/WHEEL
eaibat-0.0.11.dist-info/top_level.txt
eaibat-0.0.11.dist-info/RECORD
