Metadata-Version: 2.1
Name: eaibat
Version: 0.0.11
Summary: Basic classes to ease BDD evidence creation
Home-page: http://eaibat.readthedocs.io/
Author: Eric Aïvayan
Author-email: eric.aivayan@free.fr
License: UNKNOWN
Platform: UNKNOWN
Classifier: Development Status :: 4 - Beta
Classifier: Intended Audience :: Developers
Classifier: License :: OSI Approved :: GNU General Public License v3 (GPLv3)
Classifier: Programming Language :: Python :: 3.8
Requires-Python: >=3.7, !=2.*
Requires-Dist: behave
Requires-Dist: requests
Requires-Dist: python-docx
Requires-Dist: unidecode
